{
  "source_file": "the_truth_about_trying_to_objectify_success_marketingpsychol_krmXUK82YpY.txt",
  "primary_speaker": null,
  "concepts_addressed": [
    "Observable Reality Framework"
  ],
  "frameworks": [],
  "claims": [
    {
      "text": "Designing life around human perception and happiness is a more meaningful allocation of attention than optimizing objective measures like speed, time, duration, or cost.",
      "type": "assertion",
      "speaker": "Unknown",
      "speaker_term": null,
      "topic": "Observable Reality Framework",
      "conditions": [],
      "mechanism": null,
      "numbers": null,
      "bounded_by": []
    }
  ],
  "examples": [],
  "practices": [
    {
      "text": "Prioritize human perception and happiness in life design over optimization of economic efficiency metrics.",
      "topic": "Observable Reality Framework"
    }
  ]
}
